LICENSE
MANIFEST.in
setup.py
xtr_api/file-parser.py
xtr_api/main.py
xtr_api/normalize.py
xtr_api.egg-info/PKG-INFO
xtr_api.egg-info/SOURCES.txt
xtr_api.egg-info/dependency_links.txt
xtr_api.egg-info/top_level.txt
xtr_api/lib/__init__.py
xtr_api/lib/conf.py
xtr_api/lib/core.py
xtr_api/lib/environ.py
xtr_api/lib/misc.py
xtr_api/lib/model.py
xtr_api/lib/net.py
xtr_api/lib/os_utils.py
xtr_api/lib/setting.py
xtr_api/lib/__pycache__/__init__.cpython-311.pyc
xtr_api/lib/__pycache__/conf.cpython-311.pyc
xtr_api/lib/__pycache__/core.cpython-311.pyc
xtr_api/lib/__pycache__/environ.cpython-311.pyc
xtr_api/lib/__pycache__/misc.cpython-311.pyc
xtr_api/lib/__pycache__/model.cpython-311.pyc
xtr_api/lib/__pycache__/net.cpython-311.pyc
xtr_api/lib/__pycache__/os_utils.cpython-311.pyc
xtr_api/lib/__pycache__/setting.cpython-311.pyc
xtr_api/lib/static/__init__.py
xtr_api/lib/static/constant.py
xtr_api/lib/static/domains.py
xtr_api/lib/static/__pycache__/__init__.cpython-311.pyc
xtr_api/lib/static/__pycache__/constant.cpython-311.pyc
xtr_api/lib/static/__pycache__/domains.cpython-311.pyc
xtr_api/static/__init__.py
xtr_api/static/_info.py
xtr_api/static/__pycache__/__init__.cpython-311.pyc
xtr_api/static/__pycache__/_info.cpython-311.pyc