Metadata-Version: 2.4
Name: xtr-api
Version: 5.0.7
Summary: xtr-api
Home-page: https://github.com/choll/xtr
Download-URL: https://github.com/choll/xtr
Author: Tom Christian
Author-email: tom.christian@openxta.com
Project-URL: Documentation, https://github.com/choll/xtr
License-File: LICENSE
Dynamic: author
Dynamic: author-email
Dynamic: description
Dynamic: description-content-type
Dynamic: download-url
Dynamic: home-page
Dynamic: license-file
Dynamic: project-url
Dynamic: summary
